cli_rename/__init__.py
cli_rename/app.py
cli_rename/style.tcss
cli_rename-1.0.1.dist-info/LICENSE
cli_rename-1.0.1.dist-info/METADATA
cli_rename-1.0.1.dist-info/WHEEL
cli_rename-1.0.1.dist-info/entry_points.txt
cli_rename-1.0.1.dist-info/top_level.txt
cli_rename-1.0.1.dist-info/RECORD
