Metadata-Version: 2.1
Name: cli-rename
Version: 1.0.1
Summary: CLI version of PowerRename in PowerToys
Author-email: JCav <micojcav@outlook.com>
Project-URL: Homepage, https://github.com/GJCav/cli-rename
Project-URL: Bug Tracker, https://github.com/GJCav/cli-rename/issues
Classifier: Programming Language :: Python :: 3
Classifier: License :: OSI Approved :: GNU General Public License v3 (GPLv3)
Classifier: Operating System :: OS Independent
Classifier: Topic :: Text Processing
Classifier: Topic :: System :: Systems Administration
Classifier: Topic :: Utilities
Requires-Python: >=3.7
License-File: LICENSE
Requires-Dist: textual
